nlpfig/__init__.py
nlpfig/clean_t.py
nlpfig/utils.py
nlpfig-0.1.0.dist-info/licenses/LICENSE
nlpfig-0.1.0.dist-info/METADATA
nlpfig-0.1.0.dist-info/WHEEL
nlpfig-0.1.0.dist-info/top_level.txt
nlpfig-0.1.0.dist-info/RECORD
